tawala/__init__.py
tawala/api/__init__.py
tawala/api/backends/__init__.py
tawala/api/backends/auth.py
tawala/api/backends/server/__init__.py
tawala/api/backends/server/asgi.py
tawala/api/backends/server/wsgi.py
tawala/api/backends/storages.py
tawala/api/settings/__init__.py
tawala/api/settings/auth.py
tawala/api/settings/databases.py
tawala/api/settings/server.py
tawala/api/settings/storages.py
tawala/api/types/__init__.py
tawala/api/types/auth.py
tawala/api/types/databases.py
tawala/api/types/storages.py
tawala/api/urls.py
tawala/management/__init__.py
tawala/management/cli.py
tawala/management/commands/__init__.py
tawala/management/commands/collectstatic.py
tawala/management/commands/copy.py
tawala/management/commands/generate.py
tawala/management/commands/helpers/__init__.py
tawala/management/commands/helpers/art.py
tawala/management/commands/helpers/run.py
tawala/management/commands/runbuild.py
tawala/management/commands/runinstall.py
tawala/management/commands/runserver.py
tawala/management/commands/tailwind.py
tawala/management/settings/__init__.py
tawala/management/settings/apps.py
tawala/management/settings/generate.py
tawala/management/settings/runcommands.py
tawala/management/settings/security.py
tawala/management/settings/tailwind.py
tawala/management/settings/urls.py
tawala/management/types/__init__.py
tawala/management/types/apps.py
tawala/management/urls.py
tawala/py.typed
tawala/settings.py
tawala/types.py
tawala/ui/__init__.py
tawala/ui/admin.py
tawala/ui/settings/__init__.py
tawala/ui/settings/contactinfo.py
tawala/ui/settings/org.py
tawala/ui/settings/social.py
tawala/ui/static/ui/css/.gitignore
tawala/ui/static/ui/css/aos.css
tawala/ui/static/ui/css/bootstrap-icons.min.css
tawala/ui/static/ui/css/fonts/bootstrap-icons.woff
tawala/ui/static/ui/css/fonts/bootstrap-icons.woff2
tawala/ui/static/ui/img/apple-touch-icon.png
tawala/ui/static/ui/img/favicon.ico
tawala/ui/static/ui/img/logo.png
tawala/ui/static/ui/js/aos-init.js
tawala-1.5.4.post1.dist-info/WHEEL
tawala-1.5.4.post1.dist-info/entry_points.txt
tawala-1.5.4.post1.dist-info/METADATA
tawala-1.5.4.post1.dist-info/RECORD
