Metadata-Version: 2.3
Name: tawala
Version: 1.5.4.post1
Summary: 
Author: Kevin Wasike Wakhisi
Author-email: Kevin Wasike Wakhisi <kevin@christianwhocodes.space>
License: MIT License
Requires-Dist: christianwhocodes>=1.2.6
Requires-Dist: django>=6.0.1
Requires-Dist: django-browser-reload>=1.21.0
Requires-Dist: django-http-compression[brotli]>=1.2.0
Requires-Dist: django-minify-html>=1.14.0
Requires-Dist: django-phonenumber-field[phonenumberslite]>=8.4.0
Requires-Dist: django-watchfiles>=1.4.0
Requires-Dist: pyperclip>=1.11.0
Requires-Dist: python-dotenv>=1.2.1
Requires-Python: >=3.12
Project-URL: homepage, https://github.com/christianwhocodes/pkg-tawala#readme
Project-URL: repository, https://github.com/christianwhocodes/pkg-tawala
Project-URL: issues, https://github.com/christianwhocodes/pkg-tawala/issues
